

 {

    "version" : 2,
    "query" : "java",
    "location" : "austin, tx",
    
    "dupefilter" : true,
     
    "highlight" : true,
    
    "radius" : 25,
    
    "start" : 1,
    "end" : 10,
    "totalResults" : 1131,
     
    "pageNumber" : 0,
    

    "results" : [
        
                {
                    "jobtitle" : "Senior Software Engineer (Server)",
                    "company" : "Scientific Games",
                    "city" : "Austin",
                    "state" : "TX",
                    "country" : "US",
                    "formattedLocation" : "Austin, TX",
                    "source" : "Scientific Games",
                    "date" : "Fri, 22 Apr 2016 18:00:06 GMT",
                    "snippet" : "Experience with statically typed languages like C++, <b>Java</b>, or C#. Essential Job Functions:....",
                    "url" : "http://www.indeed.com/viewjob?jk=5fb3de6637262d7d&qd=UnHpar1Cp0nczeSgqPzBTckSZzXCbA4YGthzH8-tj78RdIPXjia8Il1dvSZwyXqeZn8TArIMt6uSMoWpiTSUQbIMLfiY0DVuvaosRQzwgQQ&indpubnum=1345414146707985&atk=1ahiad29ubs1090c",
                    "onmousedown" : "indeed_clk(this, '6310');",
                    "latitude" : 30.266483,
                    "longitude" : -97.74176,
                    "jobkey" : "5fb3de6637262d7d",
                    "sponsored" : false,
                    "expired" : false,
                    "indeedApply" : false,
                    "formattedLocationFull" : "Austin, TX",
                    "formattedRelativeTime" : "7 days ago"                
}
,
                {
                    "jobtitle" : "Sr. JAVA Programmer/Analyst",
                    "company" : "NTT DATA",
                    "city" : "Austin",
                    "state" : "TX",
                    "country" : "US",
                    "formattedLocation" : "Austin, TX",
                    "source" : "NTT DATA",
                    "date" : "Wed, 27 Apr 2016 20:07:39 GMT",
                    "snippet" : "Minimum of 5 years work experience with <b>Java</b>. <b>JAVA</b> Programmer/Analyst to join our team in Austin, TX. Reviewing/analyzing the converted code (converted from...",
                    "url" : "http://www.indeed.com/viewjob?jk=01fb92a0a8c03fe7&qd=UnHpar1Cp0nczeSgqPzBTckSZzXCbA4YGthzH8-tj78RdIPXjia8Il1dvSZwyXqeZn8TArIMt6uSMoWpiTSUQbIMLfiY0DVuvaosRQzwgQQ&indpubnum=1345414146707985&atk=1ahiad29ubs1090c",
                    "onmousedown" : "indeed_clk(this, '6310');",
                    "latitude" : 30.266483,
                    "longitude" : -97.74176,
                    "jobkey" : "01fb92a0a8c03fe7",
                    "sponsored" : false,
                    "expired" : false,
                    "indeedApply" : false,
                    "formattedLocationFull" : "Austin, TX",
                    "formattedRelativeTime" : "2 days ago"                
}
,
                {
                    "jobtitle" : "Software Applications Engineer - Java",
                    "company" : "Charles Schwab",
                    "city" : "Austin",
                    "state" : "TX",
                    "country" : "US",
                    "formattedLocation" : "Austin, TX",
                    "source" : "Charles Schwab",
                    "date" : "Fri, 29 Apr 2016 04:20:33 GMT",
                    "snippet" : "Professional experience building distributed, scalable enterprise-class applications using <b>Java</b>. Enterprise Service Bus....",
                    "url" : "http://www.indeed.com/viewjob?jk=6962c62016334b70&qd=UnHpar1Cp0nczeSgqPzBTckSZzXCbA4YGthzH8-tj78RdIPXjia8Il1dvSZwyXqeZn8TArIMt6uSMoWpiTSUQbIMLfiY0DVuvaosRQzwgQQ&indpubnum=1345414146707985&atk=1ahiad29ubs1090c",
                    "onmousedown" : "indeed_clk(this, '6310');",
                    "latitude" : 30.175825,
                    "longitude" : -97.72527,
                    "jobkey" : "6962c62016334b70",
                    "sponsored" : false,
                    "expired" : false,
                    "indeedApply" : false,
                    "formattedLocationFull" : "Austin, TX 73344",
                    "formattedRelativeTime" : "20 hours ago"                
}
,
                {
                    "jobtitle" : "Google for Work, Software Engineer",
                    "company" : "Google",
                    "city" : "Austin",
                    "state" : "TX",
                    "country" : "US",
                    "formattedLocation" : "Austin, TX",
                    "source" : "Google",
                    "date" : "Sat, 05 Mar 2016 00:54:36 GMT",
                    "snippet" : "Significant programming experience in <b>Java</b>. Programming experience in either <b>Java</b>, Objective-C or C++. Google for Work is the business unit responsible for...",
                    "url" : "http://www.indeed.com/viewjob?jk=8fcbd74ddf25d1c1&qd=UnHpar1Cp0nczeSgqPzBTckSZzXCbA4YGthzH8-tj78RdIPXjia8Il1dvSZwyXqeZn8TArIMt6uSMoWpiTSUQbIMLfiY0DVuvaosRQzwgQQ&indpubnum=1345414146707985&atk=1ahiad29ubs1090c",
                    "onmousedown" : "indeed_clk(this, '6310');",
                    "latitude" : 30.266483,
                    "longitude" : -97.74176,
                    "jobkey" : "8fcbd74ddf25d1c1",
                    "sponsored" : false,
                    "expired" : false,
                    "indeedApply" : false,
                    "formattedLocationFull" : "Austin, TX",
                    "formattedRelativeTime" : "30+ days ago"                
}
,
                {
                    "jobtitle" : "Software Engineer",
                    "company" : "University of Texas at Austin",
                    "city" : "Austin",
                    "state" : "TX",
                    "country" : "US",
                    "formattedLocation" : "Austin, TX",
                    "source" : "University of Texas at Austin",
                    "date" : "Wed, 13 Apr 2016 19:37:56 GMT",
                    "snippet" : "Experience with application development middleware such as APIs, Enterprise Service Bus (ESB, etc.), web services (REST, SOAP) and/or Enterprise Resource...",
                    "url" : "http://www.indeed.com/viewjob?jk=b1434c44360fbe52&qd=UnHpar1Cp0nczeSgqPzBTckSZzXCbA4YGthzH8-tj78RdIPXjia8Il1dvSZwyXqeZn8TArIMt6uSMoWpiTSUQbIMLfiY0DVuvaosRQzwgQQ&indpubnum=1345414146707985&atk=1ahiad29ubs1090c",
                    "onmousedown" : "indeed_clk(this, '6310');",
                    "latitude" : 30.266483,
                    "longitude" : -97.74176,
                    "jobkey" : "b1434c44360fbe52",
                    "sponsored" : false,
                    "expired" : false,
                    "indeedApply" : false,
                    "formattedLocationFull" : "Austin, TX",
                    "formattedRelativeTime" : "16 days ago"                
}
,
                {
                    "jobtitle" : "IT Software Developer",
                    "company" : "General Motors",
                    "city" : "Austin",
                    "state" : "TX",
                    "country" : "US",
                    "formattedLocation" : "Austin, TX",
                    "source" : "General Motors",
                    "date" : "Tue, 19 Apr 2016 18:44:10 GMT",
                    "snippet" : "6-10 years UI development experience using <b>JAVA</b> or .NET. IT Software Developer....",
                    "url" : "http://www.indeed.com/viewjob?jk=73de4c865fe69a72&qd=UnHpar1Cp0nczeSgqPzBTckSZzXCbA4YGthzH8-tj78RdIPXjia8Il1dvSZwyXqeZn8TArIMt6uSMoWpiTSUQbIMLfiY0DVuvaosRQzwgQQ&indpubnum=1345414146707985&atk=1ahiad29ubs1090c",
                    "onmousedown" : "indeed_clk(this, '6310');",
                    "latitude" : 30.266483,
                    "longitude" : -97.74176,
                    "jobkey" : "73de4c865fe69a72",
                    "sponsored" : false,
                    "expired" : false,
                    "indeedApply" : false,
                    "formattedLocationFull" : "Austin, TX",
                    "formattedRelativeTime" : "10 days ago"                
}
,
                {
                    "jobtitle" : "Mid-Level Software Engineer (Java)",
                    "company" : "IBM",
                    "city" : "Austin",
                    "state" : "TX",
                    "country" : "US",
                    "formattedLocation" : "Austin, TX",
                    "source" : "IBM",
                    "date" : "Sun, 17 Apr 2016 03:12:48 GMT",
                    "snippet" : "The candidate must have experience in web application development using <b>Java</b> and <b>Java</b> EE technologies including:....",
                    "url" : "http://www.indeed.com/viewjob?jk=3b783f6c94b8f236&qd=UnHpar1Cp0nczeSgqPzBTckSZzXCbA4YGthzH8-tj78RdIPXjia8Il1dvSZwyXqeZn8TArIMt6uSMoWpiTSUQbIMLfiY0DVuvaosRQzwgQQ&indpubnum=1345414146707985&atk=1ahiad29ubs1090c",
                    "onmousedown" : "indeed_clk(this, '6310');",
                    "latitude" : 30.266483,
                    "longitude" : -97.74176,
                    "jobkey" : "3b783f6c94b8f236",
                    "sponsored" : false,
                    "expired" : false,
                    "indeedApply" : false,
                    "formattedLocationFull" : "Austin, TX",
                    "formattedRelativeTime" : "12 days ago"                
}
,
                {
                    "jobtitle" : "Software Engineer",
                    "company" : "Cox Automotive",
                    "city" : "Austin",
                    "state" : "TX",
                    "country" : "US",
                    "formattedLocation" : "Austin, TX",
                    "source" : "Cox Automotive",
                    "date" : "Mon, 18 Apr 2016 22:17:34 GMT",
                    "snippet" : "This is a full-time position with vAuto, a business unit of Cox Automotive, located in Austin, TX. We are seeking an experienced web application developer to",
                    "url" : "http://www.indeed.com/viewjob?jk=10fb44b893616382&qd=UnHpar1Cp0nczeSgqPzBTckSZzXCbA4YGthzH8-tj78RdIPXjia8Il1dvSZwyXqeZn8TArIMt6uSMoWpiTSUQbIMLfiY0DVuvaosRQzwgQQ&indpubnum=1345414146707985&atk=1ahiad29ubs1090c",
                    "onmousedown" : "indeed_clk(this, '6310');",
                    "latitude" : 30.266483,
                    "longitude" : -97.74176,
                    "jobkey" : "10fb44b893616382",
                    "sponsored" : false,
                    "expired" : false,
                    "indeedApply" : false,
                    "formattedLocationFull" : "Austin, TX",
                    "formattedRelativeTime" : "11 days ago"                
}
,
                {
                    "jobtitle" : "Java Developer",
                    "company" : "NTT DATA",
                    "city" : "Austin",
                    "state" : "TX",
                    "country" : "US",
                    "formattedLocation" : "Austin, TX",
                    "source" : "NTT DATA",
                    "date" : "Wed, 20 Apr 2016 01:34:50 GMT",
                    "snippet" : "Design, build, and maintain efficient, reusable, and reliable <b>Java</b> code. A group company within NTT DATA currently seeks a <b>Java</b> Developer to join our team in...",
                    "url" : "http://www.indeed.com/viewjob?jk=66ffc596a687f0a7&qd=UnHpar1Cp0nczeSgqPzBTckSZzXCbA4YGthzH8-tj78RdIPXjia8Il1dvSZwyXqeZn8TArIMt6uSMoWpiTSUQbIMLfiY0DVuvaosRQzwgQQ&indpubnum=1345414146707985&atk=1ahiad29ubs1090c",
                    "onmousedown" : "indeed_clk(this, '6310');",
                    "latitude" : 30.266483,
                    "longitude" : -97.74176,
                    "jobkey" : "66ffc596a687f0a7",
                    "sponsored" : false,
                    "expired" : false,
                    "indeedApply" : false,
                    "formattedLocationFull" : "Austin, TX",
                    "formattedRelativeTime" : "9 days ago"                
}
,
                {
                    "jobtitle" : "Software Development Engineer",
                    "company" : "Amazon Corporate LLC",
                    "city" : "Austin",
                    "state" : "TX",
                    "country" : "US",
                    "formattedLocation" : "Austin, TX",
                    "source" : "Amazon.com",
                    "date" : "Fri, 22 Apr 2016 20:42:41 GMT",
                    "snippet" : "Knowledge of, at least, one modern programming language such as C, C++, <b>Java</b>, or Ruby. You have hundreds of thousands of hosts, hundreds of millions of lines of...",
                    "url" : "http://www.indeed.com/viewjob?jk=2d5b8dbf9628678c&qd=UnHpar1Cp0nczeSgqPzBTckSZzXCbA4YGthzH8-tj78RdIPXjia8Il1dvSZwyXqeZn8TArIMt6uSMoWpiTSUQbIMLfiY0DVuvaosRQzwgQQ&indpubnum=1345414146707985&atk=1ahiad29ubs1090c",
                    "onmousedown" : "indeed_clk(this, '6310');",
                    "latitude" : 30.444832,
                    "longitude" : -97.70863,
                    "jobkey" : "2d5b8dbf9628678c",
                    "sponsored" : false,
                    "expired" : false,
                    "indeedApply" : false,
                    "formattedLocationFull" : "Austin, TX 78728",
                    "formattedRelativeTime" : "7 days ago"                
}

    ]
}
